django_deps/__init__.py
django_deps/dependencies_map.py
django_deps/management/__init__.py
django_deps/management/commands/__init__.py
django_deps/management/commands/dependencies.py
django_deps-0.1.dist-info/LICENSE
django_deps-0.1.dist-info/METADATA
django_deps-0.1.dist-info/WHEEL
django_deps-0.1.dist-info/top_level.txt
django_deps-0.1.dist-info/RECORD
